[
  {
    "name": "چاند رامی",
    "category": "place",
    "subcategory": "village",
    "latitude": 28.329927,
    "longitude": 70.1716046,
    "id": 11631852201
  },
  {
    "name": "Rahim Yar Khan-Saddiqabad Road",
    "category": "highway",
    "subcategory": "secondary",
    "latitude": 28.333539066666667,
    "longitude": 70.17833753921569,
    "id": 762921363
  },
  {
    "name": "tertiary",
    "category": "highway",
    "subcategory": "tertiary",
    "latitude": 28.327887594736843,
    "longitude": 70.16996756842106,
    "id": 816212395
  },
  {
    "name": "unclassified",
    "category": "highway",
    "subcategory": "unclassified",
    "latitude": 28.330686114666666,
    "longitude": 70.19187088533334,
    "id": 816212399
  },
  {
    "name": "residential",
    "category": "highway",
    "subcategory": "residential",
    "latitude": 28.332372133333333,
    "longitude": 70.17900733333333,
    "id": 1038105607
  },
  {
    "name": "residential",
    "category": "highway",
    "subcategory": "residential",
    "latitude": 28.3322112,
    "longitude": 70.17798450000001,
    "id": 1038105608
  },
  {
    "name": "residential",
    "category": "highway",
    "subcategory": "residential",
    "latitude": 28.3316135,
    "longitude": 70.17789243333334,
    "id": 1038105609
  },
  {
    "name": "residential",
    "category": "highway",
    "subcategory": "residential",
    "latitude": 28.330570925,
    "longitude": 70.17564835,
    "id": 1038105610
  },
  {
    "name": "residential",
    "category": "highway",
    "subcategory": "residential",
    "latitude": 28.33125265,
    "longitude": 70.17641144999999,
    "id": 1038105611
  },
  {
    "name": "residential",
    "category": "highway",
    "subcategory": "residential",
    "latitude": 28.331964475,
    "longitude": 70.17691635,
    "id": 1038105612
  },
  {
    "name": "residential",
    "category": "highway",
    "subcategory": "residential",
    "latitude": 28.332484700000002,
    "longitude": 70.17646355,
    "id": 1038105613
  },
  {
    "name": "residential",
    "category": "highway",
    "subcategory": "residential",
    "latitude": 28.332785766666667,
    "longitude": 70.17650645555555,
    "id": 1038105614
  },
  {
    "name": "residential",
    "category": "highway",
    "subcategory": "residential",
    "latitude": 28.33140733333333,
    "longitude": 70.17499453333333,
    "id": 1038105615
  },
  {
    "name": "residential",
    "category": "highway",
    "subcategory": "residential",
    "latitude": 28.331829325,
    "longitude": 70.17456072499999,
    "id": 1038105616
  },
  {
    "name": "residential",
    "category": "highway",
    "subcategory": "residential",
    "latitude": 28.332507971428573,
    "longitude": 70.17358197142858,
    "id": 1038105617
  },
  {
    "name": "residential",
    "category": "highway",
    "subcategory": "residential",
    "latitude": 28.32850135,
    "longitude": 70.17335683333333,
    "id": 1038105618
  },
  {
    "name": "residential",
    "category": "highway",
    "subcategory": "residential",
    "latitude": 28.328385666666666,
    "longitude": 70.17370773333333,
    "id": 1038105619
  },
  {
    "name": "residential",
    "category": "highway",
    "subcategory": "residential",
    "latitude": 28.328733133333333,
    "longitude": 70.17396881666667,
    "id": 1038105620
  },
  {
    "name": "residential",
    "category": "highway",
    "subcategory": "residential",
    "latitude": 28.329425,
    "longitude": 70.1741597,
    "id": 1038105621
  },
  {
    "name": "residential",
    "category": "highway",
    "subcategory": "residential",
    "latitude": 28.329688466666667,
    "longitude": 70.17470163333333,
    "id": 1038105622
  },
  {
    "name": "residential",
    "category": "highway",
    "subcategory": "residential",
    "latitude": 28.3297157,
    "longitude": 70.17410875,
    "id": 1038105623
  },
  {
    "name": "residential",
    "category": "highway",
    "subcategory": "residential",
    "latitude": 28.33011116666667,
    "longitude": 70.1743727,
    "id": 1038105624
  },
  {
    "name": "residential",
    "category": "highway",
    "subcategory": "residential",
    "latitude": 28.32988874,
    "longitude": 70.17422624,
    "id": 1038105625
  },
  {
    "name": "residential",
    "category": "highway",
    "subcategory": "residential",
    "latitude": 28.3299435,
    "longitude": 70.172887,
    "id": 1038105626
  },
  {
    "name": "residential",
    "category": "highway",
    "subcategory": "residential",
    "latitude": 28.32995493333333,
    "longitude": 70.1733461,
    "id": 1038105627
  },
  {
    "name": "residential",
    "category": "highway",
    "subcategory": "residential",
    "latitude": 28.329845225,
    "longitude": 70.172414925,
    "id": 1038105628
  },
  {
    "name": "residential",
    "category": "highway",
    "subcategory": "residential",
    "latitude": 28.328884366666667,
    "longitude": 70.17193913333334,
    "id": 1038105629
  },
  {
    "name": "residential",
    "category": "highway",
    "subcategory": "residential",
    "latitude": 28.3285635,
    "longitude": 70.1717417,
    "id": 1038105630
  },
  {
    "name": "residential",
    "category": "highway",
    "subcategory": "residential",
    "latitude": 28.32842895,
    "longitude": 70.17158177499999,
    "id": 1038105631
  },
  {
    "name": "residential",
    "category": "highway",
    "subcategory": "residential",
    "latitude": 28.32806653333333,
    "longitude": 70.17208633333333,
    "id": 1038105632
  },
  {
    "name": "residential",
    "category": "highway",
    "subcategory": "residential",
    "latitude": 28.3288543,
    "longitude": 70.17103313333332,
    "id": 1038105633
  },
  {
    "name": "residential",
    "category": "highway",
    "subcategory": "residential",
    "latitude": 28.329173507692307,
    "longitude": 70.17191908461538,
    "id": 1038105634
  },
  {
    "name": "residential",
    "category": "highway",
    "subcategory": "residential",
    "latitude": 28.3285458,
    "longitude": 70.170999725,
    "id": 1038105635
  },
  {
    "name": "residential",
    "category": "highway",
    "subcategory": "residential",
    "latitude": 28.328827933333333,
    "longitude": 70.17030223333333,
    "id": 1038105636
  },
  {
    "name": "residential",
    "category": "highway",
    "subcategory": "residential",
    "latitude": 28.32966605,
    "longitude": 70.16979309999999,
    "id": 1038105637
  },
  {
    "name": "residential",
    "category": "highway",
    "subcategory": "residential",
    "latitude": 28.329982283333333,
    "longitude": 70.17077966666666,
    "id": 1038105638
  },
  {
    "name": "residential",
    "category": "highway",
    "subcategory": "residential",
    "latitude": 28.33021976666667,
    "longitude": 70.1702973,
    "id": 1038105639
  },
  {
    "name": "tertiary",
    "category": "highway",
    "subcategory": "tertiary",
    "latitude": 28.329912637837836,
    "longitude": 70.17471561351351,
    "id": 1038105642
  },
  {
    "name": "residential",
    "category": "highway",
    "subcategory": "residential",
    "latitude": 28.330762749999998,
    "longitude": 70.17504885,
    "id": 1308355551
  },
  {
    "name": "residential",
    "category": "highway",
    "subcategory": "residential",
    "latitude": 28.33097045,
    "longitude": 70.1746179,
    "id": 1308355552
  },
  {
    "name": "residential",
    "category": "highway",
    "subcategory": "residential",
    "latitude": 28.331380199999998,
    "longitude": 70.17459980000001,
    "id": 1308355553
  },
  {
    "name": "residential",
    "category": "highway",
    "subcategory": "residential",
    "latitude": 28.331167625,
    "longitude": 70.17420805,
    "id": 1308355554
  },
  {
    "name": "residential",
    "category": "highway",
    "subcategory": "residential",
    "latitude": 28.3321708,
    "longitude": 70.175661725,
    "id": 1308355555
  },
  {
    "name": "residential",
    "category": "highway",
    "subcategory": "residential",
    "latitude": 28.332495233333333,
    "longitude": 70.1756367,
    "id": 1308355556
  },
  {
    "name": "residential",
    "category": "highway",
    "subcategory": "residential",
    "latitude": 28.33252865,
    "longitude": 70.17461925,
    "id": 1308355557
  }
]